easyocr_unstructured.py
easyocr_unstructured-1.3.3.dist-info/METADATA
easyocr_unstructured-1.3.3.dist-info/WHEEL
easyocr_unstructured-1.3.3.dist-info/top_level.txt
easyocr_unstructured-1.3.3.dist-info/RECORD
