Metadata-Version: 2.4
Name: easyocr-unstructured
Version: 1.3.3
Summary: Parse unstructured text from PDFs
Home-page: https://github.com/shorecodeorg/easyocr-unstructured
Author: Kevin Fink
Author-email: kevin@shorecode.org
Classifier: Programming Language :: Python :: 3
Classifier: License :: OSI Approved :: MIT License
Classifier: Operating System :: OS Independent
Requires-Python: >=3.8
Requires-Dist: numpy
Requires-Dist: easyocr
Requires-Dist: pdf2image
Dynamic: author
Dynamic: author-email
Dynamic: classifier
Dynamic: description
Dynamic: description-content-type
Dynamic: home-page
Dynamic: requires-dist
Dynamic: requires-python
Dynamic: summary
